{
  "lastUpdated": "2026-07-10T20:04:51.142786",
  "tracks": [
    {
      "song": "C.R.E.A.M. (Cash Rules Everything Around Me)",
      "artist": "Wu-Tang Clan",
      "album": "Enter The Wu-Tang (36 Chambers) [Expanded Edition]",
      "played": "Jul 10, 2026",
      "albumArt": "https://i.scdn.co/image/ab67616d000048515901aaa980d3e714bf01171c",
      "spotifyUrl": "https://open.spotify.com/track/119c93MHjrDLJTApCVGpvx"
    },
    {
      "song": "Jocelyn Flores",
      "artist": "XXXTENTACION",
      "album": "17",
      "played": "Jul 10, 2026",
      "albumArt": "https://i.scdn.co/image/ab67616d00004851203c89bd4391468eea4cc3f5",
      "spotifyUrl": "https://open.spotify.com/track/7m9OqQk4RVRkw9JJdeAw96"
    },
    {
      "song": "Heartless",
      "artist": "Kanye West",
      "album": "808s & Heartbreak",
      "played": "Jul 10, 2026",
      "albumArt": "https://i.scdn.co/image/ab67616d00004851346d77e155d854735410ed18",
      "spotifyUrl": "https://open.spotify.com/track/4EWCNWgDS8707fNSZ1oaA5"
    },
    {
      "song": "Headlights",
      "artist": "Eminem, Nate Ruess",
      "album": "The Marshall Mathers LP2 (Deluxe)",
      "played": "Jul 10, 2026",
      "albumArt": "https://i.scdn.co/image/ab67616d00004851c6338d684995af10c2bf0533",
      "spotifyUrl": "https://open.spotify.com/track/222dTwr5XeEgAzEtsrQA0R"
    },
    {
      "song": "Patient",
      "artist": "Post Malone",
      "album": "Stoney (Deluxe)",
      "played": "Jul 10, 2026",
      "albumArt": "https://i.scdn.co/image/ab67616d0000485155404f712deb84d0650a4b41",
      "spotifyUrl": "https://open.spotify.com/track/5DLTuH4A5VZB2HKpqHQR6t"
    },
    {
      "song": "WAKA (feat. A Boogie Wit da Hoodie)",
      "artist": "6ix9ine, A Boogie Wit da Hoodie",
      "album": "DUMMY BOY (Revised)",
      "played": "Jul 10, 2026",
      "albumArt": "https://i.scdn.co/image/ab67616d000048510a4da3f1a72e4ecaabb76370",
      "spotifyUrl": "https://open.spotify.com/track/4uax9U22ZAdqUxTMF1beUf"
    },
    {
      "song": "What You Saying",
      "artist": "Lil Uzi Vert",
      "album": "What You Saying",
      "played": "Jul 10, 2026",
      "albumArt": "https://i.scdn.co/image/ab67616d0000485122e541a121e1c2fee630dbf3",
      "spotifyUrl": "https://open.spotify.com/track/3DjMtj3Q1gUm1wIVnVekPC"
    },
    {
      "song": "Pretty Little Fears (feat. J. Cole)",
      "artist": "6LACK, J. Cole",
      "album": "East Atlanta Love Letter",
      "played": "Jul 10, 2026",
      "albumArt": "https://i.scdn.co/image/ab67616d00004851e1530b42603367fdb2208d88",
      "spotifyUrl": "https://open.spotify.com/track/4at3d5QWnlibMVN75ECDrp"
    },
    {
      "song": "Love Me Again",
      "artist": "John Newman",
      "album": "Tribute",
      "played": "Jul 10, 2026",
      "albumArt": "https://i.scdn.co/image/ab67616d00004851b38d10a0f9eabec693d8f96e",
      "spotifyUrl": "https://open.spotify.com/track/5TbzAWWc5eJaANpA9kfGCd"
    },
    {
      "song": "Love Me Again",
      "artist": "John Newman",
      "album": "Tribute",
      "played": "Jul 10, 2026",
      "albumArt": "https://i.scdn.co/image/ab67616d00004851b38d10a0f9eabec693d8f96e",
      "spotifyUrl": "https://open.spotify.com/track/5TbzAWWc5eJaANpA9kfGCd"
    },
    {
      "song": "Stan",
      "artist": "Eminem, Dido",
      "album": "The Marshall Mathers LP",
      "played": "Jul 09, 2026",
      "albumArt": "https://i.scdn.co/image/ab67616d00004851dbb3dd82da45b7d7f31b1b42",
      "spotifyUrl": "https://open.spotify.com/track/3UmaczJpikHgJFyBTAJVoz"
    },
    {
      "song": "Plz",
      "artist": "Amara",
      "album": "Plz",
      "played": "Jul 09, 2026",
      "albumArt": "https://i.scdn.co/image/ab67616d000048515f18b916dc7e83fbe95a56f0",
      "spotifyUrl": "https://open.spotify.com/track/01zRsUiMwy2eev4L0LKZvo"
    },
    {
      "song": "Fimm",
      "artist": "BRÍET",
      "album": "Kveðja, Bríet",
      "played": "Jul 09, 2026",
      "albumArt": "https://i.scdn.co/image/ab67616d0000485165a6cb121b944cc9a6d5e752",
      "spotifyUrl": "https://open.spotify.com/track/77GxNN9ZQKnASt4sLMnTxk"
    },
    {
      "song": "Love Me Again",
      "artist": "John Newman",
      "album": "Tribute",
      "played": "Jul 09, 2026",
      "albumArt": "https://i.scdn.co/image/ab67616d00004851b38d10a0f9eabec693d8f96e",
      "spotifyUrl": "https://open.spotify.com/track/5TbzAWWc5eJaANpA9kfGCd"
    },
    {
      "song": "School Spirit",
      "artist": "Kanye West",
      "album": "The College Dropout",
      "played": "Jul 09, 2026",
      "albumArt": "https://i.scdn.co/image/ab67616d0000485125b055377757b3cdd6f26b78",
      "spotifyUrl": "https://open.spotify.com/track/1th3G3okofWlvGWAAR7Y4V"
    },
    {
      "song": "Right",
      "artist": "Mac Miller",
      "album": "Circles (Deluxe)",
      "played": "Jul 09, 2026",
      "albumArt": "https://i.scdn.co/image/ab67616d000048512f5de32853d6c64cb1d8c22b",
      "spotifyUrl": "https://open.spotify.com/track/165cwz4wGlGz0uDBhxdKLY"
    },
    {
      "song": "Into My Mother's Arms",
      "artist": "KALEO",
      "album": "Surface Sounds",
      "played": "Jul 09, 2026",
      "albumArt": "https://i.scdn.co/image/ab67616d00004851e6c0c82dce5500529fe943a3",
      "spotifyUrl": "https://open.spotify.com/track/45CtXS6ShntJUFCyWyCHnC"
    },
    {
      "song": "Deja Vu",
      "artist": "Post Malone, Justin Bieber",
      "album": "Stoney (Deluxe)",
      "played": "Jul 09, 2026",
      "albumArt": "https://i.scdn.co/image/ab67616d0000485155404f712deb84d0650a4b41",
      "spotifyUrl": "https://open.spotify.com/track/0H8XeaJunhvpBdBFIYi6Sh"
    },
    {
      "song": "Love Lost",
      "artist": "Mac Miller, The Temper Trap",
      "album": "I Love Life, Thank You",
      "played": "Jul 09, 2026",
      "albumArt": "https://i.scdn.co/image/ab67616d000048518bd48e2347b4cdaf8d6144f8",
      "spotifyUrl": "https://open.spotify.com/track/6WVdae8LbPfpOXAWuYdMnT"
    },
    {
      "song": "Emotionless",
      "artist": "Drake",
      "album": "Scorpion",
      "played": "Jul 09, 2026",
      "albumArt": "https://i.scdn.co/image/ab67616d00004851f907de96b9a4fbc04accc0d5",
      "spotifyUrl": "https://open.spotify.com/track/5Psnhdkyanjpgc2P8A5TSM"
    }
  ]
}