{
  "lastUpdated": "2026-01-12T19:01:21.110745",
  "tracks": [
    {
      "song": "Pain 1993 (with Playboi Carti)",
      "artist": "Drake, Playboi Carti",
      "album": "Dark Lane Demo Tapes",
      "played": "Jan 12, 2026",
      "albumArt": "https://i.scdn.co/image/ab67616d00004851bba7cfaf7c59ff0898acba1f",
      "spotifyUrl": "https://open.spotify.com/track/6Kj17Afjo1OKJYpf5VzCeo"
    },
    {
      "song": "Retro (Rough)",
      "artist": "Childish Gambino",
      "album": "Kauai",
      "played": "Jan 12, 2026",
      "albumArt": "https://i.scdn.co/image/ab67616d00004851811e18d061fb03580767a0f3",
      "spotifyUrl": "https://open.spotify.com/track/40DNN6CjgNEouHH0RsygcZ"
    },
    {
      "song": "Free the Slave",
      "artist": "KALEO",
      "album": "Surface Sounds",
      "played": "Jan 12, 2026",
      "albumArt": "https://i.scdn.co/image/ab67616d00004851fbe6f18abcdf1f565f34e73d",
      "spotifyUrl": "https://open.spotify.com/track/4Ux0OxCoPN8SZ9SWbGKbtT"
    },
    {
      "song": "Novacane",
      "artist": "Frank Ocean",
      "album": "Novacane",
      "played": "Jan 12, 2026",
      "albumArt": "https://i.scdn.co/image/ab67616d0000485159a428dc7ef8e0c12b0fe18a",
      "spotifyUrl": "https://open.spotify.com/track/4osgfFTICMkcGbbigdsa53"
    },
    {
      "song": "Location (feat. Burna Boy)",
      "artist": "Dave, Burna Boy",
      "album": "PSYCHODRAMA",
      "played": "Jan 12, 2026",
      "albumArt": "https://i.scdn.co/image/ab67616d00004851565f69a950084775df6a4e77",
      "spotifyUrl": "https://open.spotify.com/track/6KFWubocLBhrLs31RpEdR9"
    },
    {
      "song": "Wicked Ways",
      "artist": "Eminem",
      "album": "The Marshall Mathers LP2 (Deluxe)",
      "played": "Jan 12, 2026",
      "albumArt": "https://i.scdn.co/image/ab67616d00004851c6338d684995af10c2bf0533",
      "spotifyUrl": "https://open.spotify.com/track/4dfAUJI1QesmK5HfK9gtYs"
    },
    {
      "song": "Seriøs (feat. Amara)",
      "artist": "Roc Boyz, Amara",
      "album": "Roc Boyz, Mixtape 1",
      "played": "Jan 12, 2026",
      "albumArt": "https://i.scdn.co/image/ab67616d00004851352d50345c6be3755f743fd2",
      "spotifyUrl": "https://open.spotify.com/track/0hlygDT1sZNFPP4tIXVPMN"
    },
    {
      "song": "MOTH BALLS",
      "artist": "PARTYNEXTDOOR, Drake",
      "album": "$ome $exy $ongs 4 U",
      "played": "Jan 12, 2026",
      "albumArt": "https://i.scdn.co/image/ab67616d00004851b5a28a256eae6dc0424fef59",
      "spotifyUrl": "https://open.spotify.com/track/7DL2F2bueQycqYjqsjHYjG"
    },
    {
      "song": "Free the Slave",
      "artist": "KALEO",
      "album": "Surface Sounds",
      "played": "Jan 12, 2026",
      "albumArt": "https://i.scdn.co/image/ab67616d00004851fbe6f18abcdf1f565f34e73d",
      "spotifyUrl": "https://open.spotify.com/track/4Ux0OxCoPN8SZ9SWbGKbtT"
    },
    {
      "song": "Obsessed With You",
      "artist": "Central Cee",
      "album": "Obsessed With You",
      "played": "Jan 12, 2026",
      "albumArt": "https://i.scdn.co/image/ab67616d00004851b3f92dcb98574d7289199556",
      "spotifyUrl": "https://open.spotify.com/track/4PYfFHKfjYz6dwAtZhBy1z"
    },
    {
      "song": "DON'T KILL THE PARTY (feat. Quavo & Juicy J)",
      "artist": "Ty Dolla $ign, Juicy J, Quavo",
      "album": "TYCOON",
      "played": "Jan 12, 2026",
      "albumArt": "https://i.scdn.co/image/ab67616d00004851dcb7677617e1d7c4d5a136d7",
      "spotifyUrl": "https://open.spotify.com/track/4YmsnZcxHEGEqHB3K0vdt0"
    },
    {
      "song": "Lemonade (feat. NAV)",
      "artist": "Internet Money, Gunna, Don Toliver, NAV",
      "album": "B4 The Storm",
      "played": "Jan 12, 2026",
      "albumArt": "https://i.scdn.co/image/ab67616d00004851c4adc981dc6656e52c916088",
      "spotifyUrl": "https://open.spotify.com/track/1p0rEzrK7YtdRZVtiyV7RN"
    },
    {
      "song": "Classic",
      "artist": "MKTO",
      "album": "MKTO",
      "played": "Jan 12, 2026",
      "albumArt": "https://i.scdn.co/image/ab67616d000048519474419f15773875a495eed3",
      "spotifyUrl": "https://open.spotify.com/track/6FE2iI43OZnszFLuLtvvmg"
    },
    {
      "song": "Feels (Live)",
      "artist": "Tory Lanez",
      "album": "PLAYBOY Live",
      "played": "Jan 12, 2026",
      "albumArt": "https://i.scdn.co/image/ab67616d00004851c1e33fc690b29cf6421d348c",
      "spotifyUrl": "https://open.spotify.com/track/3aJBkLfwLa5rOujkUL698Q"
    },
    {
      "song": "It Will Rain",
      "artist": "Bruno Mars",
      "album": "It Will Rain",
      "played": "Jan 12, 2026",
      "albumArt": "https://i.scdn.co/image/ab67616d00004851dec2e6bae5062b94fc4eeb84",
      "spotifyUrl": "https://open.spotify.com/track/0M3HkE321xpCbCYqVKzr1q"
    },
    {
      "song": "Good For You",
      "artist": "Selena Gomez, A$AP Rocky",
      "album": "Good For You",
      "played": "Jan 12, 2026",
      "albumArt": "https://i.scdn.co/image/ab67616d00004851aad6fe0c229e8272edbce251",
      "spotifyUrl": "https://open.spotify.com/track/5XfywqPX6XBOdYQNbOaQvy"
    },
    {
      "song": "Rolls Royce Umbrella (with Chris Brown)",
      "artist": "Clever, Chris Brown",
      "album": "Crazy",
      "played": "Jan 12, 2026",
      "albumArt": "https://i.scdn.co/image/ab67616d00004851f12575a4d54c0ee98665fd32",
      "spotifyUrl": "https://open.spotify.com/track/2Yv6DfAVcjugchZpZKv5P7"
    },
    {
      "song": "What Do You Mean?",
      "artist": "Justin Bieber",
      "album": "Purpose (Deluxe)",
      "played": "Jan 12, 2026",
      "albumArt": "https://i.scdn.co/image/ab67616d00004851f46b9d202509a8f7384b90de",
      "spotifyUrl": "https://open.spotify.com/track/4B0JvthVoAAuygILe3n4Bs"
    },
    {
      "song": "Rifa",
      "artist": "P-Flow",
      "album": "Rifa",
      "played": "Jan 12, 2026",
      "albumArt": "https://i.scdn.co/image/ab67616d000048518912f4943501b7ef6eb00c76",
      "spotifyUrl": "https://open.spotify.com/track/16uqX7W5hC7ljyl2UpcfjV"
    },
    {
      "song": "GREECE (feat. Drake)",
      "artist": "DJ Khaled, Drake",
      "album": "GREECE (feat. Drake)",
      "played": "Jan 12, 2026",
      "albumArt": "https://i.scdn.co/image/ab67616d000048517db0d21fc5696a3fcedfb933",
      "spotifyUrl": "https://open.spotify.com/track/35RJhm1pEovTBwnNR0zWad"
    }
  ]
}